ez_setup.py
setup.py
pysage/__init__.py
pysage/messaging.py
pysage/system.py
pysage/util.py
pysage.egg-info/PKG-INFO
pysage.egg-info/SOURCES.txt
pysage.egg-info/dependency_links.txt
pysage.egg-info/top_level.txt
tests/__init__.py
tests/test_groups.py
tests/test_messaging.py
tests/test_system.py