Metadata-Version: 1.0
Name: pysage
Version: 1.2.1
Summary: pysage
Home-page: http://code.google.com/p/pysage/
Author: John S. Yang
Author-email: bigjhnny@gmail.com
License: MIT
Keywords: distributed python publisher-subscriber,message-passing,object management library
Platform: UNKNOWN
